MANIFEST.in
readme.md
setup.py
voice_gender/__init__.py
voice_gender/features.py
voice_gender.egg-info/PKG-INFO
voice_gender.egg-info/SOURCES.txt
voice_gender.egg-info/dependency_links.txt
voice_gender.egg-info/requires.txt
voice_gender.egg-info/top_level.txt
voice_gender/models/females.gmm
voice_gender/models/males.gmm