Metadata-Version: 1.0
Name: voice-gender
Version: 0.2.3
Summary: recognize gender
Home-page: https://github.com/JarbasAl/voice-gender
Author: jarbasAI
Author-email: jarbasai@mailfence.com
License: MIT
Platform: UNKNOWN
